bip44/__init__.py
bip44/consts.py
bip44/utils.py
bip44/wallet.py
bip44-0.1.5.dist-info/LICENSE
bip44-0.1.5.dist-info/METADATA
bip44-0.1.5.dist-info/WHEEL
bip44-0.1.5.dist-info/RECORD
