Metadata-Version: 2.1
Name: bip44
Version: 0.1.5
Summary: Simple Python bip44 implementation. Mnemonic + bip32.
Home-page: https://github.com/kigawas/python-bip44
License: MIT
Keywords: bitcoin,ethereum,elliptic curves,cryptocurrency,blockchain
Author: Weiliang Li
Author-email: to.be.impressive@gmail.com
Maintainer: Weiliang Li
Maintainer-email: to.be.impressive@gmail.com
Requires-Python: >=3.8.1,<4.0.0
Classifier: License :: OSI Approved :: MIT License
Classifier: Programming Language :: Python :: 3
Classifier: Programming Language :: Python :: 3.9
Classifier: Programming Language :: Python :: 3.10
Classifier: Programming Language :: Python :: 3.11
Classifier: Programming Language :: Python :: 3.12
Classifier: Programming Language :: Python :: 3.13
Requires-Dist: bip32 (>=3.4)
Requires-Dist: mnemonic (>=0.20)
Requires-Dist: pycryptodome (>=3.19.1)
Project-URL: Repository, https://github.com/kigawas/python-bip44
